{
  "$schema": "https://developer.microsoft.com/json-schemas/fabric/item/report/definition/visualContainer/2.3.0/schema.json",
  "name": "14619515524e8c383e0a",
  "position": {
    "x": 0,
    "y": 86.58524670249146,
    "z": 1000,
    "height": 45.83924825426017,
    "width": 320,
    "tabOrder": 1000
  },
  "visual": {
    "visualType": "textbox",
    "objects": {
      "general": [
        {
          "properties": {
            "paragraphs": [
              {
                "textRuns": [
                  {
                    "value": "Visit our weekly dataviz challenge",
                    "textStyle": {
                      "fontFamily": "Segoe UI Light",
                      "fontSize": "16pt",
                      "color": "#666666"
                    }
                  }
                ]
              }
            ]
          }
        }
      ]
    },
    "visualContainerObjects": {
      "background": [
        {
          "properties": {
            "show": {
              "expr": {
                "Literal": {
                  "Value": "false"
                }
              }
            }
          }
        }
      ]
    },
    "drillFilterOtherVisuals": true
  },
  "parentGroupName": "f97be30915728b51c0a0"
}